<?xml version="1.0" encoding="utf-8" standalone="yes"?>
<Task TaskName="FD Challenger-Log Discrepancy-Mandatory" Desc="FD Challenger-Log Discrepancy-Mandatory" TaskID="21fec78fe2164f22ad282f1309b200f6" Path="FD Challenger-Log Discrepancy-Mandatory.XML">
  <Step StepId="4" stepSeq="1" ObjectId="" ObjectTypeId="" ActionId="bcffb579c3aa4cf0aa4138767b39063d" ActionName="StoreVariable" QClass="com.webdriverfw.Wrappers.General" Comment="" isCommented="False" IsSkipped="false" ObjectName="">
    <Param Name="&quot;Type&quot;" ParamSeq="1" Parameterized="0" Data="Type">
    </Param>
    <Param Name="&quot;MandatoryValidations&quot;" ParamSeq="2" Parameterized="0" Data="MandatoryValidations">
    </Param>
  </Step>
  <Step StepId="3" stepSeq="2" ObjectId="" ObjectTypeId="" ActionId="347ba1d54a3c47c49ad3fb47aa2e67a0" ActionName="label_Based_standard_input_operation" QClass="customActions.SFDC_Standard_Functions" Comment="" isCommented="False" IsSkipped="false" ObjectName="">
    <Param Name="&quot;Discrepancy Type&quot;" ParamSeq="1" Parameterized="0" Data="Discrepancy Type">
    </Param>
    <Param Name="Discrepancy Type" ParamSeq="2" Parameterized="1" Data="">
    </Param>
    <Param Name="&quot;MandatoryValidations&quot;" ParamSeq="3" Parameterized="0" Data="MandatoryValidations">
    </Param>
  </Step>
  <Step StepId="2" stepSeq="3" ObjectId="" ObjectTypeId="" ActionId="347ba1d54a3c47c49ad3fb47aa2e67a0" ActionName="label_Based_standard_input_operation" QClass="customActions.SFDC_Standard_Functions" Comment="" isCommented="False" IsSkipped="false" ObjectName="">
    <Param Name="&quot;Status&quot;" ParamSeq="1" Parameterized="0" Data="Status">
    </Param>
    <Param Name="Status" ParamSeq="2" Parameterized="1" Data="">
    </Param>
    <Param Name="&quot;MandatoryValidations&quot;" ParamSeq="3" Parameterized="0" Data="MandatoryValidations">
    </Param>
  </Step>
</Task>